russ/__init__.py
russ/convert.py
russ/dataset.py
russ/evaluate.py
russ/lstm.py
russ/syllables.py
russ/tokenizer.py
russ/train.py
russ/parsers/__init__.py
russ/parsers/espeak_stress.py
russ/parsers/inflected_stress.py
russ/parsers/wiki_stress.py
russ/stress/__init__.py
russ/stress/dict.py
russ/stress/model.py
russ/stress/predictor.py
russ/tests/__init__.py
russ/tests/test_stress_model.py
russ/tests/test_stress_reader.py
scripts/__init__.py
scripts/create_stress_dict.py
scripts/parse_opcorpora.py
scripts/prepare_data.py
russ-0.0.2.dist-info/LICENSE
russ-0.0.2.dist-info/METADATA
russ-0.0.2.dist-info/NOTICE
russ-0.0.2.dist-info/WHEEL
russ-0.0.2.dist-info/top_level.txt
russ-0.0.2.dist-info/RECORD
